yoyodyne/__init__.py
yoyodyne/callbacks.py
yoyodyne/defaults.py
yoyodyne/metrics.py
yoyodyne/optimizers.py
yoyodyne/schedulers.py
yoyodyne/sizing.py
yoyodyne/special.py
yoyodyne/trainers.py
yoyodyne/util.py
yoyodyne/cli/__init__.py
yoyodyne/cli/hyperparameters.py
yoyodyne/cli/main.py
yoyodyne/cli/sweep.py
yoyodyne/data/__init__.py
yoyodyne/data/batches.py
yoyodyne/data/collators.py
yoyodyne/data/datamodules.py
yoyodyne/data/datasets.py
yoyodyne/data/indexes.py
yoyodyne/data/mappers.py
yoyodyne/data/tsv.py
yoyodyne/models/__init__.py
yoyodyne/models/base.py
yoyodyne/models/beam_search.py
yoyodyne/models/embeddings.py
yoyodyne/models/expert.py
yoyodyne/models/hard_attention.py
yoyodyne/models/pointer_generator.py
yoyodyne/models/rnn.py
yoyodyne/models/transducer.py
yoyodyne/models/transformer.py
yoyodyne/models/modules/__init__.py
yoyodyne/models/modules/attention.py
yoyodyne/models/modules/base.py
yoyodyne/models/modules/generation_probability.py
yoyodyne/models/modules/hard_attention.py
yoyodyne/models/modules/linear.py
yoyodyne/models/modules/position.py
yoyodyne/models/modules/rnn.py
yoyodyne/models/modules/transformer.py
yoyodyne-0.5.2.dist-info/licenses/LICENSE.txt
yoyodyne-0.5.2.dist-info/METADATA
yoyodyne-0.5.2.dist-info/WHEEL
yoyodyne-0.5.2.dist-info/entry_points.txt
yoyodyne-0.5.2.dist-info/top_level.txt
yoyodyne-0.5.2.dist-info/RECORD
