Metadata-Version: 2.4
Name: yoyodyne
Version: 0.5.2
Summary: Small-vocabulary neural sequence-to-sequence models
Author: Adam Wiemerslage, Travis M. Bartley
Author-email: Kyle Gorman <kylebgorman@gmail.com>
License: Apache 2.0
Project-URL: homepage, https://github.com/CUNY-CL/yoyodyne
Keywords: computational linguistics,morphology,natural language processing,language
Classifier: Programming Language :: Python :: 3.10
Classifier: Programming Language :: Python :: 3.11
Classifier: Programming Language :: Python :: 3.12
Classifier: Programming Language :: Python :: 3.13
Classifier: Programming Language :: Python :: 3.14
Classifier: Development Status :: 4 - Beta
Classifier: Environment :: Console
Classifier: License :: OSI Approved :: Apache Software License
Classifier: Operating System :: OS Independent
Classifier: Topic :: Text Processing :: Linguistic
Requires-Python: <3.15,>=3.10
License-File: LICENSE.txt
Requires-Dist: PyYAML<7.0.0,>=6.0.2
Requires-Dist: jsonargparse[signatures]<5.0.0,>=4.40.0
Requires-Dist: lightning==2.6.0
Requires-Dist: maxwell>=0.2.6
Requires-Dist: numpy<3.0.0,>=2.0.0
Requires-Dist: omegaconf==2.3.0
Requires-Dist: torch==2.9.1
Requires-Dist: torchmetrics==1.8.2
Requires-Dist: wandb<0.19.8,>=0.18.7
Dynamic: license-file
